microt_prompt_matrix/__init__.py
microt_prompt_matrix/main_ema.py
microt_prompt_matrix/main_uema.py
microt_prompt_matrix/feature_engineering_ema/__init__.py
microt_prompt_matrix/feature_engineering_ema/battery_level.py
microt_prompt_matrix/feature_engineering_ema/compliance.py
microt_prompt_matrix/feature_engineering_ema/day_of_the_week.py
microt_prompt_matrix/feature_engineering_ema/days_in_study.py
microt_prompt_matrix/feature_engineering_ema/home_location.py
microt_prompt_matrix/feature_engineering_ema/location.py
microt_prompt_matrix/feature_engineering_ema/location_label.py
microt_prompt_matrix/feature_engineering_ema/mims_summary.py
microt_prompt_matrix/feature_engineering_ema/parts_of_waking_hour.py
microt_prompt_matrix/feature_engineering_ema/phone_detected_activity.py
microt_prompt_matrix/feature_engineering_ema/phone_lock.py
microt_prompt_matrix/feature_engineering_ema/screen_status.py
microt_prompt_matrix/feature_engineering_ema/study_mode.py
microt_prompt_matrix/feature_engineering_ema/time_of_the_day.py
microt_prompt_matrix/feature_engineering_ema/waking_hours.py
microt_prompt_matrix/feature_engineering_ema/prompt_response/__init__.py
microt_prompt_matrix/feature_engineering_ema/prompt_response/combine_appended_response.py
microt_prompt_matrix/feature_engineering_ema/prompt_response/preprocess_promptResponse_raw.py
microt_prompt_matrix/feature_engineering_uema/__init__.py
microt_prompt_matrix/feature_engineering_uema/battery_level.py
microt_prompt_matrix/feature_engineering_uema/compliance.py
microt_prompt_matrix/feature_engineering_uema/day_of_the_week.py
microt_prompt_matrix/feature_engineering_uema/days_in_study.py
microt_prompt_matrix/feature_engineering_uema/home_location.py
microt_prompt_matrix/feature_engineering_uema/location.py
microt_prompt_matrix/feature_engineering_uema/location_label.py
microt_prompt_matrix/feature_engineering_uema/mims_summary.py
microt_prompt_matrix/feature_engineering_uema/parts_of_waking_hour.py
microt_prompt-0.1.22.dist-info/LICENSE.txt
microt_prompt-0.1.22.dist-info/METADATA
microt_prompt-0.1.22.dist-info/WHEEL
microt_prompt-0.1.22.dist-info/top_level.txt
microt_prompt-0.1.22.dist-info/RECORD
